odoo/addons/eremu_berriak/.gitignore
odoo/addons/eremu_berriak/__init__.py
odoo/addons/eremu_berriak/__manifest__.py
odoo/addons/eremu_berriak/controllers/__init__.py
odoo/addons/eremu_berriak/controllers/controllers.py
odoo/addons/eremu_berriak/demo/demo.xml
odoo/addons/eremu_berriak/models/__init__.py
odoo/addons/eremu_berriak/models/mantenance_equipment.py
odoo/addons/eremu_berriak/security/ir.model.access.csv
odoo/addons/eremu_berriak/views/eremuBerriak_bista.xml
odoo/addons/eremu_berriak/views/templates.xml
odoo/addons/eremu_berriak/views/views.xml
odoo_addon_eremu_berriak-16.0.1.0.0.dist-info/METADATA
odoo_addon_eremu_berriak-16.0.1.0.0.dist-info/WHEEL
odoo_addon_eremu_berriak-16.0.1.0.0.dist-info/top_level.txt
odoo_addon_eremu_berriak-16.0.1.0.0.dist-info/RECORD
