Metadata-Version: 2.1
Name: odoo-addon-eremu-berriak
Version: 16.0.1.0.0
Summary: Herentzia bidez mantenuko ekipoei eremu berriak gehitzeko modulua
Home-page: https://fpzornotzalh.eus/
Author: Zornotza LHII Infor
License: UNKNOWN
Platform: UNKNOWN
Classifier: Programming Language :: Python
Classifier: Framework :: Odoo
Classifier: Framework :: Odoo :: 16.0
Requires-Python: >=3.10
Requires-Dist: odoo (<16.1dev,>=16.0a)
